openxmllib/__init__.py
openxmllib/contenttypes.py
openxmllib/document.py
openxmllib/namespaces.py
openxmllib/presentation.py
openxmllib/shell.py
openxmllib/spreadsheet.py
openxmllib/utils.py
openxmllib/wordprocessing.py
openxmllib_py3-2.0.0.dist-info/COPYING
openxmllib_py3-2.0.0.dist-info/METADATA
openxmllib_py3-2.0.0.dist-info/WHEEL
openxmllib_py3-2.0.0.dist-info/entry_points.txt
openxmllib_py3-2.0.0.dist-info/top_level.txt
openxmllib_py3-2.0.0.dist-info/RECORD
