Metadata-Version: 2.1
Name: openxmllib-py3
Version: 2.0.0
Summary: Provides resources to handle OpenXML documents.
Home-page: https://github.com/wilbertom/openxmllib-py3
Author: Wilberto Morales
Author-email: wilbertomorales777@gmail.com
License: GPLv2
Keywords: Python OpenXML lxml Office2007 ECMA376
Platform: UNKNOWN
Classifier: License :: OSI Approved :: GNU General Public License (GPL)
Classifier: Topic :: Office/Business :: Office Suites
Classifier: Topic :: Software Development :: Libraries :: Python Modules
Classifier: Topic :: Text Processing :: Indexing
Classifier: Programming Language :: Python
Requires-Dist: lxml (>=3.4.0)
